fc16004uno/__init__.py
fc16004uno/lineal/__init__.py
fc16004uno/lineal/cramer.py
fc16004uno/lineal/descomposicion_lu.py
fc16004uno/lineal/eliminacion_gauss.py
fc16004uno/lineal/gauss_jordan.py
fc16004uno/lineal/gauss_seidel.py
fc16004uno/lineal/jacobi.py
fc16004uno/no_lineal/__init__.py
fc16004uno/no_lineal/biseccion.py
fc16004uno-0.1.0.dist-info/licenses/LICENSE
tests/__init__.py
tests/test_lineal.py
tests/test_no_lineal.py
fc16004uno-0.1.0.dist-info/METADATA
fc16004uno-0.1.0.dist-info/WHEEL
fc16004uno-0.1.0.dist-info/top_level.txt
fc16004uno-0.1.0.dist-info/RECORD
